pySISF/__init__.py
pySISF/sisf.py
pySISF/sndif_utils.py
pySISF/vidlib.py
pysisf-0.5.3.dist-info/licenses/LICENSE
pysisf-0.5.3.dist-info/WHEEL
pysisf-0.5.3.dist-info/METADATA
pysisf-0.5.3.dist-info/RECORD
